COPYRIGHT.txt
LICENSE.txt
MANIFEST.in
README.md
setup.py
tests/queue/__init__.py
tests/queue/test_file.py
tests/queue/test_multisqs.py
tests/queue/test_sqs.py
tilequeue/__init__.py
tilequeue/command.py
tilequeue/config.py
tilequeue/metatile.py
tilequeue/metro_extract.py
tilequeue/postgresql.py
tilequeue/process.py
tilequeue/query.py
tilequeue/store.py
tilequeue/tile.py
tilequeue/top_tiles.py
tilequeue/transform.py
tilequeue/utils.py
tilequeue/wof.py
tilequeue/worker.py
tilequeue.egg-info/PKG-INFO
tilequeue.egg-info/SOURCES.txt
tilequeue.egg-info/dependency_links.txt
tilequeue.egg-info/entry_points.txt
tilequeue.egg-info/not-zip-safe
tilequeue.egg-info/requires.txt
tilequeue.egg-info/top_level.txt
tilequeue/format/__init__.py
tilequeue/format/geojson.py
tilequeue/format/mvt.py
tilequeue/format/topojson.py
tilequeue/format/vtm.py
tilequeue/format/OSciMap4/GeomEncoder.py
tilequeue/format/OSciMap4/TileData_v4_pb2.py
tilequeue/format/OSciMap4/__init__.py
tilequeue/format/OSciMap4/pbf_test.py
tilequeue/format/OSciMap4/StaticKeys/__init__.py
tilequeue/format/OSciMap4/StaticVals/__init__.py
tilequeue/format/OSciMap4/TagRewrite/__init__.py
tilequeue/queue/__init__.py
tilequeue/queue/file.py
tilequeue/queue/memory.py
tilequeue/queue/multisqs.py
tilequeue/queue/redis_queue.py
tilequeue/queue/sqs.py
tilequeue/toi/__init__.py
tilequeue/toi/file.py
tilequeue/toi/s3.py