Metadata-Version: 1.1
Name: tilequeue
Version: 1.9.0
Summary: Queue operations to manage the processes surrounding tile rendering.
Home-page: https://github.com/mapzen/tilequeue
Author: Robert Marianski, Mapzen
Author-email: rob@mapzen.com
License: MIT
Keywords: aws queue s3 sqs tile map
Platform: UNKNOWN
Classifier: Development Status :: 4 - Beta
Classifier: Environment :: Console
Classifier: Intended Audience :: Developers
Classifier: Intended Audience :: System Administrators
Classifier: License :: OSI Approved :: MIT License
Classifier: Natural Language :: English
Classifier: Operating System :: POSIX :: Linux
Classifier: Programming Language :: Python :: 2.7
Classifier: Programming Language :: Python :: Implementation :: CPython
Classifier: Topic :: Internet :: WWW/HTTP :: Site Management
Classifier: Topic :: Utilities
